maxbits/__init__.py
maxbits-1.0.2.dist-info/LICENSE
maxbits-1.0.2.dist-info/METADATA
maxbits-1.0.2.dist-info/WHEEL
maxbits-1.0.2.dist-info/top_level.txt
maxbits-1.0.2.dist-info/RECORD
