Metadata-Version: 2.1
Name: maxbits
Version: 1.0.2
Summary: A Python module that provides functions to calculate the maximum and minimum values for signed and unsigned integers, as well as floating-point numbers of specified bit widths.
Home-page: https://github.com/woskethebot/maxbits
Author: woskethebot
Author-email: nushratakhter1999@gmail.com
Classifier: Programming Language :: Python :: 3
Classifier: License :: OSI Approved :: Mozilla Public License 2.0 (MPL 2.0)
Classifier: Operating System :: OS Independent
Requires-Python: >=3.10
License-File: LICENSE
